{
    "loaders": [
        {
            "id": "MARVEL RIVALS EXT",
            "name": "MARVEL RIVALS EXT",
            "categoryId": "others",
            "downloadUrl": "https://raw.githubusercontent.com/avod245/752951673818710049_cloud/main/MARVELRIVALS.exe",
            "status": "online"
        },
        {
            "id": "EXODUS SPOOFER CLEANER",
            "name": "EXODUS SPOOFER CLEANER",
            "categoryId": "spoofers",
            "downloadUrl": "https://raw.githubusercontent.com/avod245/752951673818710049_cloud/main/Exodus_Spoofer.exe",
            "status": "online"
        },
        {
            "id": "BOSS UNLOCKER",
            "name": "BOSS UNLOCKER",
            "categoryId": "bo6",
            "downloadUrl": "https://raw.githubusercontent.com/avod245/752951673818710049_cloud/main/BOSS_UNLOCKER.exe",
            "status": "online"
        },
        {
            "id": "RECOIL.IO",
            "name": "RECOIL.IO",
            "categoryId": "bo6",
            "downloadUrl": "https://raw.githubusercontent.com/avod245/752951673818710049_cloud/main/Elite_Recoil_Reducer.exe",
            "status": "online"
        },
        {
            "id": "CAUTION SUPPORT TOOL",
            "name": "CAUTION SUPPORT TOOL",
            "categoryId": "others",
            "downloadUrl": "https://raw.githubusercontent.com/avod245/752951673818710049_cloud/main/cautionSupportTool.exe",
            "status": "online"
        },
        {
            "id": "K1 INTERNAL",
            "name": "K1 INTERNAL",
            "categoryId": "bo6",
            "downloadUrl": "https://raw.githubusercontent.com/avod245/752951673818710049_cloud/main/K1INT.exe",
            "status": "online"
        }
    ]
}